bluesky_mcp/__init__.py
bluesky_mcp/server.py
iflow_mcp_bluesky_mcp_server-0.1.1.dist-info/METADATA
iflow_mcp_bluesky_mcp_server-0.1.1.dist-info/WHEEL
iflow_mcp_bluesky_mcp_server-0.1.1.dist-info/entry_points.txt
iflow_mcp_bluesky_mcp_server-0.1.1.dist-info/licenses/LICENSE
iflow_mcp_bluesky_mcp_server-0.1.1.dist-info/RECORD
